external_markdown/__init__.py
external_markdown/plugin.py
mkdocs_embed_markdown-3.0.2.dist-info/LICENSE.md
mkdocs_embed_markdown-3.0.2.dist-info/METADATA
mkdocs_embed_markdown-3.0.2.dist-info/WHEEL
mkdocs_embed_markdown-3.0.2.dist-info/entry_points.txt
mkdocs_embed_markdown-3.0.2.dist-info/top_level.txt
mkdocs_embed_markdown-3.0.2.dist-info/RECORD
