Metadata-Version: 2.1
Name: mkdocs-embed-markdown
Version: 3.0.2
Summary: Mkdocs plugin that allow to inject external markdown or markdown section from given url
Author-email: yanedie <zinyi073@gmail.com>
License: MIT
Project-URL: Source, https://github.com/yanedie/mkdocs-embed-external-markdown
Keywords: mkdocs,plugin,markdown,external-markdown,embed,external,markdown-section
Classifier: License :: OSI Approved :: MIT License
Classifier: Programming Language :: Python :: 3.9
Requires-Python: >=3.9
License-File: LICENSE.md
Requires-Dist: requests >=2.3.0
